gd_util/__init__.py
gd_util/datacontainer/__init__.py
gd_util/datacontainer/container.py
gd_util/datagraph/__init__.py
gd_util/datagraph/mesh_datagraph.py
gd_util/mesh/__init__.py
gd_util/mesh/mesh.py
gd_util/parameterspace/__init__.py
gd_util/parameterspace/optimisation_parameters.py
gd_util/parameterspace/param_iter.py
gd_util/parameterspace/parameter_space.py
gd_util/parameterspace/simulation_parameters.py
gd_util/parameterspace/utils.py
gd_util/utils/__init__.py
gd_util/utils/io.py
gd_util/utils/make_bar.py
gd_util-0.0.5.dist-info/licenses/LICENSE
gd_util-0.0.5.dist-info/METADATA
gd_util-0.0.5.dist-info/WHEEL
gd_util-0.0.5.dist-info/top_level.txt
gd_util-0.0.5.dist-info/RECORD
