Metadata-Version: 2.4
Name: gd-util
Version: 0.0.5
Requires-Python: <3.14,>=3.9
License-File: LICENSE
Requires-Dist: numpy
Requires-Dist: treelib
Requires-Dist: PyYAML
Requires-Dist: matplotlib
Requires-Dist: pandas
Requires-Dist: param
Requires-Dist: pymoo
Requires-Dist: smt
Requires-Dist: vtk
Requires-Dist: pyvista
Requires-Dist: meshio
Requires-Dist: pymmg
Dynamic: license-file
